{
"items": [
{
"title": "「我是教练」功能升级！一站搞定排兵布阵，战术大师就是你！",
"img": "https://bdimg7.qunliao.info/fastdfs8/M00/38/A5/rBXRn2oz6YeAOc4FAANbLYqLatw356.jpg",
"link": "https://www.dongqiudi.com/article/5946741",
"time": 1781787361
},
{
"title": "梅西世界杯16球看图闯关｜二十年青春回忆，你能满分通关吗？",
"img": "https://bdimg7.qunliao.info/fastdfs8/M00/35/82/rBXRn2oyvtOAFzVZABTpa9Er2b4350.jpg",
"link": "https://www.dongqiudi.com/article/5944142",
"time": 1781710591
},
{
"title": "世界杯第八比赛日前瞻：墨西哥韩国盼连胜，加拿大瑞士争登顶",
"img": "https://bdimg7.qunliao.info/fastdfs8/M00/38/2D/rBXRDGozte6Ac0PZAFJk-fzo8q8619.jpg",
"link": "https://www.dongqiudi.com/article/5945827",
"time": 1781776800
},
{
"title": "英格兰赛后复盘：流放太子扶正凯恩，中后场危机潜藏",
"img": "https://bdimg7.qunliao.info/fastdfs8/M00/37/FC/rBXRn2ozp1eARfLsAAh3F5SCnwY637.jpg",
"link": "https://www.dongqiudi.com/article/5945680",
"time": 1781776800
},
{
"title": "B组潜在头名之争！超百位专家已就位，全场28钻限时特价！",
"img": "https://bdimg7.qunliao.info/fastdfs8/M00/38/30/rBXRn2ozu3OACaNIAACFaXOQEVM072.jpg",
"link": "https://www.dongqiudi.com/article/5946281",
"time": 1781778502
},
{
"title": "TA重排世界杯实力榜：法国阿根廷英格兰前三，葡萄牙第十",
"img": "https://bdimg7.qunliao.info/fastdfs8/M00/38/C0/rBXRn2oz9QqADsICAAJCETQLE0M739.jpg",
"link": "https://www.dongqiudi.com/article/5946855",
"time": 1781790172
},
{
"title": "因第五跖骨骨折缺阵，费尔明：别担心，我很快就会回来",
"img": "https://bdimg7.qunliao.info/fastdfs8/M00/38/C1/rBXRn2oz9YSADiTAAAEBnp6VcYA831.jpg",
"link": "https://www.dongqiudi.com/article/5946854",
"time": 1781790096
},
{
"title": "Tycsports：波施疑似下颌骨折，或无缘剩余赛事",
"img": "https://bdimg7.qunliao.info/fastdfs8/M00/38/BF/rBXRn2oz9JSAYPsdAAGgolAC-OA829.jpg",
"link": "https://www.dongqiudi.com/article/5946852",
"time": 1781789955
},
{
"title": "全市场：罗马有意扎帕科斯塔，转会费或低于1000万欧",
"img": "https://bdimg7.qunliao.info/fastdfs8/M00/38/B4/rBXRn2oz7-uAQiCeAAD132M3bII621.jpg",
"link": "https://www.dongqiudi.com/article/5946846",
"time": 1781789923
},
{
"title": "米体：尤文前腰伊尔迪兹已摆脱小腿伤势，土耳其盼他救赎球队",
"img": "https://bdimg7.qunliao.info/fastdfs8/M00/38/B4/rBXRn2oz7-mASWnFAAFlAQnZpVc450.jpg",
"link": "https://www.dongqiudi.com/article/5946843",
"time": 1781789821
},
{
"title": "巴萨16名球员参加世界杯，只有3人在首轮取得胜利",
"img": "https://bdimg7.qunliao.info/fastdfs8/M00/29/E6/rBXRn2ouUsGALzgGAADW4rhHBQM587.jpg",
"link": "https://www.dongqiudi.com/article/5946839",
"time": 1781789815
},
{
"title": "每体：皇马正按穆帅要求重建阵容，卡马文加或遭牺牲",
"img": "https://bdimg7.qunliao.info/fastdfs8/M00/37/91/rBXRDGozdhGAcv90AADR3Tcn6os095.jpg",
"link": "https://www.dongqiudi.com/article/5946828",
"time": 1781789685
},
{
"title": "莫雷托：米兰还在追求克勒舍，看看之后会不会有更明确的进展",
"img": "https://bdimg7.qunliao.info/fastdfs8/M00/25/E8/rBXRDGkE2OuAdidWAAEGa74K7aA839.jpg",
"link": "https://www.dongqiudi.com/article/5946819",
"time": 1781789537
},
{
"title": "阿马德世界杯34分钟6次过人，是02年德尼尔森后第一人",
"img": "https://bdimg7.qunliao.info/fastdfs8/M00/38/C8/rBXRDGoz8wyAXUttAAPG9EMDv6s066.jpg",
"link": "https://www.dongqiudi.com/article/5946835",
"time": 1781789499
},
{
"title": "踢球者：完成萨伊瓦里和布朗的引援后，拜仁目标出售帕利尼亚等4人",
"img": "https://bdimg7.qunliao.info/fastdfs8/M00/38/C5/rBXRDGoz8jmABHdlAAFJX0iC2t0594.jpg",
"link": "https://www.dongqiudi.com/article/5946827",
"time": 1781789270
},
{
"title": "佛得角“中国造”体育场中方援建者：逼平西班牙我一点不惊讶",
"img": "https://bdimg7.qunliao.info/fastdfs8/M00/38/B8/rBXRn2oz8cCABHkEAAD9Y6lC8-o212.jpg",
"link": "https://www.dongqiudi.com/article/5946816",
"time": 1781789147
},
{
"title": "利物浦队史百大球星第48名：米尔纳",
"img": "https://bdimg7.qunliao.info/fastdfs8/M00/38/C4/rBXRDGoz8ZCAXw3LAAOgVWT_Kkc003.jpg",
"link": "https://www.dongqiudi.com/article/5946805",
"time": 1781789131
},
{
"title": "记者布雷：梅西母亲称他们很激动，正享受一切",
"img": "https://bdimg7.qunliao.info/fastdfs8/M00/38/C4/rBXRDGoz8PiAB57CAAGxhAWBQ48566.jpg",
"link": "https://www.dongqiudi.com/article/5946811",
"time": 1781788935
},
{
"title": "帕拉蒂奇谈佛罗伦萨夏窗规划：未排除莫伊塞-基恩离队",
"img": "https://bdimg7.qunliao.info/fastdfs8/M00/38/B4/rBXRDGoz6vCAZICpAAy0HcXu3WY171.jpg",
"link": "https://www.dongqiudi.com/article/5946804",
"time": 1781788773
},
{
"title": "德天空：维克托-穆尼奥斯转会利物浦将于本周完成并官宣",
"img": "https://bdimg7.qunliao.info/fastdfs8/M00/38/B4/rBXRn2oz77uAdevRAAZAbwosCeM251.jpg",
"link": "https://www.dongqiudi.com/article/5946801",
"time": 1781788629
}
]
}