{
"items": [
{
"title": "四年之约，你还记得当时的约定吗？快来重温当年的世界杯祈愿",
"img": "https://bdimg7.qunliao.info/fastdfs8/M00/5A/AE/rBXRn2pA6b-Ac7RRACpv7uZKj7k679.png",
"link": "https://www.dongqiudi.com/article/5975688",
"time": 1782642000
},
{
"title": "招人嫌的萨内很失败，只能用他的德国更悲哀",
"img": "https://bdimg7.qunliao.info/fastdfs8/M00/61/38/rBXRDGpDXRSAEPcPABXkP1Faswo819.jpg",
"link": "https://www.dongqiudi.com/article/5982373",
"time": 1782813600
},
{
"title": "捂嘴=红牌？试试这套卷子，看看你会不会直接掏牌！",
"img": "https://bdimg7.qunliao.info/fastdfs8/M00/61/6D/rBXRDGpDcJyAT9EgAAIP4z6lr38764.png",
"link": "https://www.dongqiudi.com/article/5982590",
"time": 1782804651
},
{
"title": "法国淘汰赛经验丰富，瑞典初次登台，心态是最大变量？看专家如何解读>>",
"img": "https://bdimg7.qunliao.info/fastdfs8/M00/61/27/rBXRn2pDXDuAGtzbAACBHLFK3UE471.jpg",
"link": "https://www.dongqiudi.com/article/5981536",
"time": 1782781815
},
{
"title": "德弗赖告别国米：我会永远把共同经历的每一份情感珍藏在心中",
"img": "https://bdimg7.qunliao.info/fastdfs8/M00/62/34/rBXRn2pDwoiADBM_AAxTDKTlPiY199.png",
"link": "https://www.dongqiudi.com/article/5983574",
"time": 1782825616
},
{
"title": "官方：摩纳哥中场迪亚塔合同到期离队",
"img": "https://bdimg7.qunliao.info/fastdfs8/M00/62/31/rBXRn2pDwO2AbKsjAAIL0ChRxKU355.jpg",
"link": "https://www.dongqiudi.com/article/5983561",
"time": 1782825312
},
{
"title": "施罗德谈德国队出局：你不可能总是赢，跌倒了就站起来",
"img": "https://bdimg7.qunliao.info/fastdfs8/M00/62/32/rBXRDGpDub-AGKiMAAAxwBKUVAk856.jpg",
"link": "https://www.dongqiudi.com/article/5983555",
"time": 1782825261
},
{
"title": "双响+绝杀，韦世豪当选中超官方第16轮最佳球员",
"img": "https://bdimg7.qunliao.info/fastdfs8/M00/62/41/rBXRDGpDwPqAXBD1AAC1S3AmcHc945.jpg",
"link": "https://www.dongqiudi.com/article/5983558",
"time": 1782825255
},
{
"title": "沙尔克官方：球队年轻前锋雷默特租借加盟杜伊斯堡，为期一年",
"img": "https://bdimg7.qunliao.info/fastdfs8/M00/62/2F/rBXRn2pDwFCAHO3uABHzZGRGFl0824.png",
"link": "https://www.dongqiudi.com/article/5983559",
"time": 1782825124
},
{
"title": "利物浦评队史百大球星第12名：罗比-福勒",
"img": "https://bdimg7.qunliao.info/fastdfs8/M00/62/2F/rBXRn2pDwDWAR20DAANBfnYcJcw113.jpg",
"link": "https://www.dongqiudi.com/article/5983535",
"time": 1782825058
},
{
"title": "西足协视听版权收入增长至1.173亿欧元，赞助达到8070万欧元",
"img": "https://bdimg7.qunliao.info/fastdfs8/M00/62/3C/rBXRDGpDvsKAfKn8AAMnv6hgoU0770.jpg",
"link": "https://www.dongqiudi.com/article/5983531",
"time": 1782824994
},
{
"title": "罗体：加纳巫师诅咒阿根廷被淘汰，球迷刷屏留言化解厄运",
"img": "https://bdimg7.qunliao.info/fastdfs8/M00/4B/10/rBXRDGo7BDuABkK0AAHMx07vV94533.jpg",
"link": "https://www.dongqiudi.com/article/5983544",
"time": 1782824988
},
{
"title": "米体：米兰转向盯上伊纳西奥，该球员被标价4000万欧",
"img": "https://bdimg7.qunliao.info/fastdfs8/M00/62/23/rBXRn2pDuvGASBg8AAE5w7Hfbac451.jpg",
"link": "https://www.dongqiudi.com/article/5983529",
"time": 1782824781
},
{
"title": "罗马诺：诺伊尔确认退出国家队",
"img": "https://bdimg7.qunliao.info/fastdfs8/M00/62/3C/rBXRDGpDvoGAIJaRAAKFlSZgImU280.jpg",
"link": "https://www.dongqiudi.com/article/5983527",
"time": 1782824631
},
{
"title": "意媒：马尔蒂尼仍观望意足协技术总监邀约，他对此兴趣不大",
"img": "https://bdimg7.qunliao.info/fastdfs8/M00/62/24/rBXRn2pDu1eAHtboAA5h2nr_vGE506.jpg",
"link": "https://www.dongqiudi.com/article/5983506",
"time": 1782824514
},
{
"title": "卡洛斯：巴西的翻盘剧本我再熟悉不过，这和皇马的逆转很相似",
"img": "https://bdimg7.qunliao.info/fastdfs8/M00/62/37/rBXRDGpDvN-AX_EUAAH_9lYqOpU890.jpg",
"link": "https://www.dongqiudi.com/article/5983497",
"time": 1782824184
},
{
"title": "弗兰：穆斯莱拉发烧到41度，贝尔萨却半场才知情",
"img": "https://bdimg7.qunliao.info/fastdfs8/M00/62/23/rBXRn2pDuwyAbWmuAABovlHMwus530.jpg",
"link": "https://www.dongqiudi.com/article/5983504",
"time": 1782824050
},
{
"title": "切-亚当斯告别世界杯：我们已拼尽全力，还是差了最后一点点",
"img": "https://bdimg7.qunliao.info/fastdfs8/M00/62/18/rBXRn2pDtjOAEHW-AADcz85TPWQ062.jpg",
"link": "https://www.dongqiudi.com/article/5983484",
"time": 1782823729
},
{
"title": "图片报：第六轮点球很多德国国脚回避责任，塔主动站出来面对压力",
"img": "https://bdimg7.qunliao.info/fastdfs8/M00/62/22/rBXRn2pDuiuAMtXuAAEbk845wac416.jpg",
"link": "https://www.dongqiudi.com/article/5983479",
"time": 1782823580
},
{
"title": "都体：尤文加速追逐埃热那亚20岁埃哈托尔，已谈妥2031年合同",
"img": "https://bdimg7.qunliao.info/fastdfs8/M00/61/73/rBXRDGpDcwCAbjiZAAHzO6cEJdg261.jpg",
"link": "https://www.dongqiudi.com/article/5983475",
"time": 1782823326
}
]
}