{
"items": [
{
"title": "阿尔及利亚2-1逆转约旦送对手出局，本布阿利、古伊里破门",
"img": "https://bdimg7.qunliao.info/fastdfs8/M00/48/90/rBXRDGo6E9yAR6C4AD3twzTvUcM269.jpg",
"link": "https://www.dongqiudi.com/article/5959581",
"time": 1782190853
},
{
"title": "C罗首轮哑火，今天能找回状态吗？看看专家分析>>",
"img": "https://bdimg7.qunliao.info/fastdfs8/M00/48/D6/rBXRDGo6MIiAdzYZAACBHLFK3UE888.jpg",
"link": "https://www.dongqiudi.com/article/5958393",
"time": 1782147678
},
{
"title": "厄德高：外界的批评对我影响不大，这就是生活",
"img": "https://bdimg7.qunliao.info/fastdfs8/M00/49/16/rBXRDGo6SvuAGSQSAAesED9qobc553.jpg",
"link": "https://www.dongqiudi.com/article/5960033",
"time": 1782205189
},
{
"title": "周二世界杯四场伤停情报：迪亚斯伤愈回归；英格兰可能轮换",
"img": "https://bdimg7.qunliao.info/fastdfs8/M00/49/12/rBXRDGo6ScCAPDBxABVzXBaFyik506.png",
"link": "https://www.dongqiudi.com/article/5960042",
"time": 1782205107
},
{
"title": "马马杜忆加盟英博：上网看到梭鱼湾的氛围，第二天就签合同了",
"img": "https://bdimg7.qunliao.info/fastdfs8/M00/49/15/rBXRDGo6Sm6AYGhUAAEj20szL5Q582.jpg",
"link": "https://www.dongqiudi.com/article/5960031",
"time": 1782205095
},
{
"title": "TA：曼城对托纳利的兴趣浓厚；罗德里目前还没有续约的迹象",
"img": "https://bdimg7.qunliao.info/fastdfs8/M00/49/09/rBXRn2o6Sj6AUspyAADH12MrCQA284.jpg",
"link": "https://www.dongqiudi.com/article/5959969",
"time": 1782205062
},
{
"title": "周二世界杯四场伤停情报：迪亚斯伤愈回归；英格兰可能轮换",
"img": "https://bdimg7.qunliao.info/fastdfs8/M00/49/12/rBXRDGo6ScCAPDBxABVzXBaFyik506.png",
"link": "https://www.dongqiudi.com/article/5960029",
"time": 1782204869
},
{
"title": "铃木唯人：世界杯是球员梦寐以求的舞台，我不想沉醉于首秀",
"img": "https://bdimg7.qunliao.info/fastdfs8/M00/49/11/rBXRDGo6SNqAT0HgAAPK1fU-l9U345.jpg",
"link": "https://www.dongqiudi.com/article/5960014",
"time": 1782204705
},
{
"title": "记者：皇马对弗兰-加西亚要价2000万欧，与贝蒂斯谈判已停滞",
"img": "https://bdimg7.qunliao.info/fastdfs8/M00/49/05/rBXRn2o6SM2AbbnhAANfSyGzamk851.jpg",
"link": "https://www.dongqiudi.com/article/5960022",
"time": 1782204689
},
{
"title": "全市场：谢尔德鲁普身价涨至3000万欧，多队有意",
"img": "https://bdimg7.qunliao.info/fastdfs8/M00/49/04/rBXRDGo6Q3-ATy1YAAFaygqZjAg334.jpg",
"link": "https://www.dongqiudi.com/article/5959999",
"time": 1782204631
},
{
"title": "邮报：夏奇拉“被强吻”系误会，亲吻者是儿子米兰",
"img": "https://bdimg7.qunliao.info/fastdfs8/M00/49/0C/rBXRDGo6R02AEMlaAAEd9tjVRIk470.jpg",
"link": "https://www.dongqiudi.com/article/5960015",
"time": 1782204535
},
{
"title": "中村敬斗：两场比赛都能参与进球，算是发挥出了我的特点",
"img": "https://bdimg7.qunliao.info/fastdfs8/M00/48/FF/rBXRn2o6RpqARyvTAATYP3z5SLc954.jpg",
"link": "https://www.dongqiudi.com/article/5960001",
"time": 1782204079
},
{
"title": "每体：拉科鲁尼亚正式更名皇家拉科鲁尼亚体育",
"img": "https://bdimg7.qunliao.info/fastdfs8/M00/46/BE/rBXRn2o5cniAHNq0AAEbK9s94kw859.jpg",
"link": "https://www.dongqiudi.com/article/5959982",
"time": 1782203962
},
{
"title": "前田大然：瑞典拥有杀伤力极强的双前锋；我们一定会拿下他们",
"img": "https://bdimg7.qunliao.info/fastdfs8/M00/48/FA/rBXRn2o6RHqAdZ6UAAFyfDlmCU0470.jpg",
"link": "https://www.dongqiudi.com/article/5959981",
"time": 1782203569
},
{
"title": "克罗地亚vs巴拿马：L组抢分战；傅明担任助理视频助理裁判",
"img": "https://bdimg7.qunliao.info/fastdfs8/M00/48/32/rBXRDGo57_WAZyQ6ACE_0Fo5jhU949.png",
"link": "https://www.dongqiudi.com/article/5959396",
"time": 1782203372
},
{
"title": "6.23世界杯赛前情报速递：迪亚斯伤愈回归；克罗地亚背水一战",
"img": "https://bdimg7.qunliao.info/fastdfs8/M00/48/F7/rBXRn2o6QoaAQ8p1ACCpJZSe4K8618.png",
"link": "https://www.dongqiudi.com/article/5959988",
"time": 1782203351
},
{
"title": "瑟洛特：我们原本的目标就是小组出线，我们做到了",
"img": "https://bdimg7.qunliao.info/fastdfs8/M00/49/02/rBXRDGo6QmWANXHPAATeErAmMhA907.jpg",
"link": "https://www.dongqiudi.com/article/5959959",
"time": 1782203026
},
{
"title": "罗体：罗马追格林伍德，准备继续加码报价",
"img": "https://bdimg7.qunliao.info/fastdfs8/M00/43/63/rBXRDGo4EW2AJ0smAAIl3CT9wK0970.jpg",
"link": "https://www.dongqiudi.com/article/5959973",
"time": 1782202994
},
{
"title": "博主：根据辽宁铁人官方发布的视频，此前外租的吴明屿已归队",
"img": "https://bdimg7.qunliao.info/fastdfs8/M00/48/F6/rBXRn2o6QjSAXY5ZAAB7jZWvY3A769.jpg",
"link": "https://www.dongqiudi.com/article/5959972",
"time": 1782202935
},
{
"title": "队报：法国3-0胜伊拉克后返波士顿，训练推迟1小时",
"img": "https://bdimg7.qunliao.info/fastdfs8/M00/48/FD/rBXRDGo6QAKAVhzZAALWTtkonTE485.jpg",
"link": "https://www.dongqiudi.com/article/5959955",
"time": 1782202487
}
]
}