{
"items": [
{
"title": "记者：罗杰斯加盟切尔西1.17亿镑为固定转会费，不含浮动",
"img": "https://bdimg7.qunliao.info/fastdfs8/M00/A8/30/rBXRn2pb8faAQjykAACVRGUp1iw634.jpg",
"link": "https://www.dongqiudi.com/article/6050939",
"time": 1784410764
},
{
"title": "洛佩特吉：理论上压迫西班牙很简单，实际执行起来却非常困难",
"img": "https://bdimg7.qunliao.info/fastdfs8/M00/A8/2C/rBXRn2pb8JiAfhiwAAE5sHdnjL8905.jpg",
"link": "https://www.dongqiudi.com/article/6050918",
"time": 1784410419
},
{
"title": "TA：雷暴取消西班牙队世界杯决赛前最后一次训练",
"img": "https://bdimg7.qunliao.info/fastdfs8/M00/A8/25/rBXRDGpb6jOAEPGlAAAZH4eHMDQ802.jpg",
"link": "https://www.dongqiudi.com/article/6050869",
"time": 1784410334
},
{
"title": "0-2落后英格兰，法国自2008年以来首次在开场20分钟落后两球",
"img": "https://bdimg7.qunliao.info/fastdfs8/M00/A8/35/rBXRDGpb79CACD1MAAUMGumS-GY129.jpg",
"link": "https://www.dongqiudi.com/article/6050919",
"time": 1784410194
},
{
"title": "0-2落后英格兰，法国首次在世界杯开场20分钟内丢两球",
"img": "https://bdimg7.qunliao.info/fastdfs8/M00/A8/26/rBXRn2pb7s2ATym6ACdbltAnGGo848.jpg",
"link": "https://www.dongqiudi.com/article/6050914",
"time": 1784410041
},
{
"title": "赖斯破门为世界杯季军战第3快，世界杯最快进球也诞生在季军战",
"img": "https://bdimg7.qunliao.info/fastdfs8/M00/A8/27/rBXRn2pb73qAWeEzAAD1mIwjFhk548.jpg",
"link": "https://www.dongqiudi.com/article/6050916",
"time": 1784410021
},
{
"title": "马克龙：法国足球翻开新一页，感谢德尚带来的传奇胜利",
"img": "https://bdimg7.qunliao.info/fastdfs8/M00/A8/1F/rBXRn2pb7IiAMvMnAAFPOgzqkqQ262.jpg",
"link": "https://www.dongqiudi.com/article/6050892",
"time": 1784410015
},
{
"title": "第12次世界杯出场，赖斯斩获个人生涯世界杯首球",
"img": "https://bdimg7.qunliao.info/fastdfs8/M00/A8/24/rBXRn2pb7heAOAStAAE6mjK14Bc969.jpg",
"link": "https://www.dongqiudi.com/article/6050901",
"time": 1784409852
},
{
"title": "自2010年以来，法国首次连续两场世界杯至少丢两球",
"img": "https://bdimg7.qunliao.info/fastdfs8/M00/A8/26/rBXRn2pb7s2ATym6ACdbltAnGGo848.jpg",
"link": "https://www.dongqiudi.com/article/6050909",
"time": 1784409810
},
{
"title": "法足协主席：感谢德尚的伟大贡献；本月底才会宣布新帅人选",
"img": "https://bdimg7.qunliao.info/fastdfs8/M00/A8/19/rBXRn2pb6q6AVT0WAAAUxUDg-6I452.jpg",
"link": "https://www.dongqiudi.com/article/6050873",
"time": 1784409779
},
{
"title": "赖斯134秒破门，为英格兰自2020欧洲杯决赛以来正赛最快进球",
"img": "https://bdimg7.qunliao.info/fastdfs8/M00/A8/20/rBXRn2pb7USABDhjAALe7Cz__2M106.jpg",
"link": "https://www.dongqiudi.com/article/6050898",
"time": 1784409651
},
{
"title": "法国队开场3分钟丢球，是球队自1982年以来世界杯最快失球",
"img": "https://bdimg7.qunliao.info/fastdfs8/M00/A8/2A/rBXRDGpb69eAJRy6AAFK9n8jTlw661.jpg",
"link": "https://www.dongqiudi.com/article/6050877",
"time": 1784409314
},
{
"title": "开场134秒破门，赖斯打入英格兰自1982年以来世界杯最快进球",
"img": "https://bdimg7.qunliao.info/fastdfs8/M00/A8/2C/rBXRDGpb7MKAbF9jAA_8ja22yrk345.png",
"link": "https://www.dongqiudi.com/article/6050886",
"time": 1784409288
},
{
"title": "克林斯曼：西班牙对阵阿根廷会很精彩，梅西最后总能解决比赛",
"img": "https://bdimg7.qunliao.info/fastdfs8/M00/A8/0D/rBXRn2pb59iAE-tDAAFCN-hkNyM912.jpg",
"link": "https://www.dongqiudi.com/article/6050833",
"time": 1784408467
},
{
"title": "罗马诺：罗马想下周初敲定萨默维尔，因为维拉有可能参与竞争",
"img": "https://bdimg7.qunliao.info/fastdfs8/M00/A8/21/rBXRDGpb6XSAGfuXAAGlU8M5zuk676.jpg",
"link": "https://www.dongqiudi.com/article/6050832",
"time": 1784408442
},
{
"title": "担任英格兰队大赛首发队长，赖斯是阿森纳球员第二人",
"img": "https://bdimg7.qunliao.info/fastdfs8/M00/A8/0D/rBXRn2pb556ABpZxAAFa5zAhHog160.jpg",
"link": "https://www.dongqiudi.com/article/6050825",
"time": 1784408128
},
{
"title": "图赫尔：半决赛法国完全不在状态没能赢；这场我们会全力争胜",
"img": "https://bdimg7.qunliao.info/fastdfs8/M00/A8/09/rBXRn2pb5jSAct5LAAIRTjeLoNc987.jpg",
"link": "https://www.dongqiudi.com/article/6050805",
"time": 1784407914
},
{
"title": "记者：雅克松和德拉普预计将有一人离队",
"img": "https://bdimg7.qunliao.info/fastdfs8/M00/A8/0C/rBXRn2pb5x2AVarmAAIcvPtneE4463.jpg",
"link": "https://www.dongqiudi.com/article/6050817",
"time": 1784407890
},
{
"title": "切尔西跟队：维拉在罗杰斯转会谈判中询问了雅克松的情况",
"img": "https://bdimg7.qunliao.info/fastdfs8/M00/A8/06/rBXRn2pb5XiAIU5UAADWLr56pU8630.jpg",
"link": "https://www.dongqiudi.com/article/6050796",
"time": 1784407561
}
]
}