{
"items": [
{
"title": "法国3-1塞内加尔，姆巴佩双响，巴尔科拉建功，奥利塞献助攻",
"img": "https://bdimg7.qunliao.info/fastdfs8/M00/32/D9/rBXRDGoxuEeAUTZyAAMypU4uWcI235.jpg",
"link": "https://www.dongqiudi.com/article/5941405",
"time": 1781643900
},
{
"title": "梅西领衔出战，卫冕冠军能否打破魔咒？超百位专家为你解读！",
"img": "https://bdimg7.qunliao.info/fastdfs8/M00/32/3B/rBXRDGoxegSAUiPwAACFaXOQEVM831.jpg",
"link": "https://www.dongqiudi.com/article/5941092",
"time": 1781647200
},
{
"title": "懂球帝海报：法兰西最锋利的剑",
"img": "https://bdimg7.qunliao.info/fastdfs8/M00/32/E9/rBXRDGoxvTyAFENRAASY0wUEUVk285.jpg",
"link": "https://n.dongqiudi.com/webapp/tops.html?id=5941458",
"time": 1781644703
},
{
"title": "每体：瓦伦西亚已敲定3笔引援，目前各位置仍有明显补强需求",
"img": "https://bdimg7.qunliao.info/fastdfs8/M00/2B/6E/rBXRn2ou6nOAClRVAAGjcuhRwLg985.jpg",
"link": "https://www.dongqiudi.com/article/5941628",
"time": 1781649714
},
{
"title": "评论员：你们得向姆巴佩道歉，他在穆帅麾下单赛季能进60球",
"img": "https://bdimg7.qunliao.info/fastdfs8/M00/33/11/rBXRn2ox0MKAWeuJAAH1f5DFjTM668.jpg",
"link": "https://www.dongqiudi.com/article/5941656",
"time": 1781649682
},
{
"title": "状态延续，哈兰德在挪威国家队近11场正式比赛都有进球",
"img": "https://bdimg7.qunliao.info/fastdfs8/M00/33/11/rBXRn2ox0QWADiVBAAw1JV2DPdI872.png",
"link": "https://www.dongqiudi.com/article/5941654",
"time": 1781649671
},
{
"title": "哈兰德世界杯首秀就打入进球，挪威上一次踢世界杯他还没出生",
"img": "https://bdimg7.qunliao.info/fastdfs8/M00/33/19/rBXRDGoxz8WAHSANAAGyRH8qfks729.jpg",
"link": "https://www.dongqiudi.com/article/5941647",
"time": 1781649386
},
{
"title": "萨利巴：姆巴佩具备打破纪录的一切，希望本届世界杯就能做到",
"img": "https://bdimg7.qunliao.info/fastdfs8/M00/33/0C/rBXRn2oxzpSAJXNGAAFvGj4u1IA058.jpg",
"link": "https://www.dongqiudi.com/article/5941644",
"time": 1781649259
},
{
"title": "全市场：都灵计划向博洛尼亚门将拉瓦利亚提出一份租借报价",
"img": "https://bdimg7.qunliao.info/fastdfs8/M00/33/04/rBXRn2oxy4mAY1rIAAB1Vo1L6GA910.jpg",
"link": "https://www.dongqiudi.com/article/5941625",
"time": 1781649158
},
{
"title": "帕普-盖伊：我也说不清问题出在哪，接下来要全力赢下剩余两场",
"img": "https://bdimg7.qunliao.info/fastdfs8/M00/33/13/rBXRDGoxzYGAPbjKAAEdRFOnRE0319.jpg",
"link": "https://www.dongqiudi.com/article/5941634",
"time": 1781648961
},
{
"title": "佩杜拉：国米已与普罗韦德尔达成协议，48小时内将再次接洽",
"img": "https://bdimg7.qunliao.info/fastdfs8/M00/1F/5B/rBXRn2oqW-aALxfpAAFu11DEq24956.jpg",
"link": "https://www.dongqiudi.com/article/5941629",
"time": 1781648677
},
{
"title": "每体：若没有伤病，世界杯上孔德很可能会继续占据首发位置",
"img": "https://bdimg7.qunliao.info/fastdfs8/M00/33/00/rBXRn2oxybaAOBRiAAHlYAiusfQ876.jpg",
"link": "https://www.dongqiudi.com/article/5941610",
"time": 1781648503
},
{
"title": "阿尔及利亚球迷：足球对我们来说就像氧气，它是很多人的快乐来源",
"img": "https://bdimg7.qunliao.info/fastdfs8/M00/33/05/rBXRn2oxy-qAEfXLAACqPaTlbdw723.jpg",
"link": "https://www.dongqiudi.com/article/5941620",
"time": 1781648448
},
{
"title": "老贝弟弟：马尔彭萨机场该以我哥命名，米兰市长做法令人不齿",
"img": "https://bdimg7.qunliao.info/fastdfs8/M00/33/11/rBXRDGoxy_OAcAyiAAIQhIU8Q_E937.jpg",
"link": "https://www.dongqiudi.com/article/5941626",
"time": 1781648447
},
{
"title": "老贝弟弟：国米尤文各有各的好，但米兰的过去也是梦寐以求的",
"img": "https://bdimg7.qunliao.info/fastdfs8/M00/33/03/rBXRn2oxyvGAC9SHAAIU8421oFM870.jpg",
"link": "https://www.dongqiudi.com/article/5941619",
"time": 1781648347
},
{
"title": "TA：挪威出线概率高达78%，若战胜伊拉克将升至92%",
"img": "https://bdimg7.qunliao.info/fastdfs8/M00/31/CF/rBXRDGoxSbmAY9xEADDtJaiA4QM544.jpg",
"link": "https://www.dongqiudi.com/article/5941616",
"time": 1781648251
},
{
"title": "意天空：佛罗伦萨盯上科莱奥肖，伯恩利要价900-1000万欧元",
"img": "https://bdimg7.qunliao.info/fastdfs8/M00/32/F9/rBXRn2oxxzGAT3M0AACn4gpngwA558.jpg",
"link": "https://www.dongqiudi.com/article/5941575",
"time": 1781648210
},
{
"title": "曼晚：阿莫林有意签下乌加特，门德斯已开始与米兰谈转会",
"img": "https://bdimg7.qunliao.info/fastdfs8/M00/32/FC/rBXRn2oxx66AFcSYAAFLDznEG-k625.jpg",
"link": "https://www.dongqiudi.com/article/5941592",
"time": 1781648098
}
]
}