{
"items": [
{
"title": "Here we go！罗马诺：米兰超7000万欧签下贡萨洛-拉莫斯",
"img": "https://bdimg7.qunliao.info/fastdfs8/M00/54/96/rBXRDGo-sXWAHeD9AAuWf00Zcv0023.jpg",
"link": "https://www.dongqiudi.com/article/5969612",
"time": 1782493618
},
{
"title": "数据漂亮的哈兰德VS冠军底蕴的姆巴佩，绝代双骄相信谁？专家意见>>",
"img": "https://bdimg7.qunliao.info/fastdfs8/M00/53/18/rBXRDGo-FBKAAz-kAACBHLFK3UE460.jpg",
"link": "https://www.dongqiudi.com/article/5967463",
"time": 1782439370
},
{
"title": "罗马诺：在米兰夏窗能买的前锋中贡萨洛已是前三，不给超高价巴黎绝不会卖",
"img": "https://bdimg7.qunliao.info/fastdfs8/M00/54/C9/rBXRn2o-yWCAYs4RAAGFS8felkc993.jpg",
"link": "https://www.dongqiudi.com/article/5969768",
"time": 1782500421
},
{
"title": "123456",
"img": "https://bdimg7.qunliao.info/fastdfs8/M00/54/D0/rBXRn2o-zBCAOLZ7AAB-3cdsYP4463.jpg",
"link": "https://www.dongqiudi.com/article/5969783",
"time": 1782500384
},
{
"title": "索尔巴肯：赛程间隔很短，轮换是为了给体能更好的球员机会",
"img": "https://bdimg7.qunliao.info/fastdfs8/M00/54/D8/rBXRDGo-yi6AbKF6AAG7wIsJdsc034.jpg",
"link": "https://www.dongqiudi.com/article/5969770",
"time": 1782500167
},
{
"title": "TA：皇马从未考虑回购帕斯后卖给其他俱乐部，这也不符合规定",
"img": "https://bdimg7.qunliao.info/fastdfs8/M00/54/CA/rBXRn2o-yWuAJWd5AADIUS3M7Lo358.jpg",
"link": "https://www.dongqiudi.com/article/5969766",
"time": 1782500165
},
{
"title": "奥利弗执法第5场世界杯比赛，距英格兰裁判的最高纪录只差1场",
"img": "https://bdimg7.qunliao.info/fastdfs8/M00/54/D5/rBXRDGo-yOuAAOvXAAlfC7DBdnI181.png",
"link": "https://www.dongqiudi.com/article/5969760",
"time": 1782499801
},
{
"title": "全市场：科莫试探引进皮西利遭罗马拒绝",
"img": "https://bdimg7.qunliao.info/fastdfs8/M00/54/BB/rBXRDGo-vsyALTmYAAEbkMJ8RBo014.jpg",
"link": "https://www.dongqiudi.com/article/5969716",
"time": 1782499358
},
{
"title": "27岁188天，姆巴佩是完成15场世界杯首发最年轻球员",
"img": "https://bdimg7.qunliao.info/fastdfs8/M00/54/C7/rBXRDGo-xCuAMqQJAARH-nKcaiU078.jpg",
"link": "https://www.dongqiudi.com/article/5969732",
"time": 1782498552
},
{
"title": "战法国挪威轮换多达10名球员，世界杯历史并列第二",
"img": "https://bdimg7.qunliao.info/fastdfs8/M00/54/C9/rBXRDGo-xKOACiLbAAIP7Q0SmCQ582.jpg",
"link": "https://www.dongqiudi.com/article/5969743",
"time": 1782498514
},
{
"title": "每体：门德斯正在运作卡萨多加盟米兰的潜在交易",
"img": "https://bdimg7.qunliao.info/fastdfs8/M00/C3/34/rBXRDGoFr3eAUECqAAFVOTbraXc468.jpg",
"link": "https://www.dongqiudi.com/article/5969737",
"time": 1782498330
},
{
"title": "马丁内斯：如果阿根廷能继续取得辉煌成就，我也完全不会意外",
"img": "https://bdimg7.qunliao.info/fastdfs8/M00/54/B7/rBXRn2o-wquAPOeUAAR_eKSmmLY487.jpg",
"link": "https://www.dongqiudi.com/article/5969731",
"time": 1782498065
},
{
"title": "记者：科莫在谈引进达文森-桑切斯，加拉塔萨雷要1500万欧",
"img": "https://bdimg7.qunliao.info/fastdfs8/M00/54/B9/rBXRn2o-wvaAcTVlAADjHC-3jRI988.jpg",
"link": "https://www.dongqiudi.com/article/5969730",
"time": 1782498045
},
{
"title": "马丁内斯：2018年率比利时击败英格兰让整支球队都成长了很多",
"img": "https://bdimg7.qunliao.info/fastdfs8/M00/54/C2/rBXRDGo-wguAbA2RAARymF7vjOg673.jpg",
"link": "https://www.dongqiudi.com/article/5969725",
"time": 1782497926
},
{
"title": "邮报：阿森纳准备第二次报价吉马良斯，纽卡仍坚持非卖品立场",
"img": "https://bdimg7.qunliao.info/fastdfs8/M00/54/B5/rBXRn2o-wc6AGElLAAERZSz6D54554.jpg",
"link": "https://www.dongqiudi.com/article/5969722",
"time": 1782497850
},
{
"title": "马丁内斯：我们是要先踢好运动战才能更好地利用定位球的球队",
"img": "https://bdimg7.qunliao.info/fastdfs8/M00/54/B5/rBXRn2o-wYSAd0xfAARsPImrqjU712.jpg",
"link": "https://www.dongqiudi.com/article/5969718",
"time": 1782497779
},
{
"title": "马丁内斯：第二场比赛极具说服力的表现为我们注入了巨大信心",
"img": "https://bdimg7.qunliao.info/fastdfs8/M00/54/BC/rBXRDGo-v82AANPaAARXtymDjx4371.jpg",
"link": "https://www.dongqiudi.com/article/5969572",
"time": 1782497646
}
]
}