{
"items": [
{
"title": "32强对阵出炉！快来大胆预测一波你的冠军之路",
"img": "https://bdimg7.qunliao.info/fastdfs8/M00/59/F3/rBXRn2pAoGSACWQQAABJ90Jjbdo606.jpg",
"link": "https://www.dongqiudi.com/article/5840489",
"time": 1780200000
},
{
"title": "官方：韩国队主帅洪明甫宣布辞职",
"img": "https://bdimg7.qunliao.info/fastdfs8/M00/5B/9B/rBXRDGpBQQ2ALOF4AAGrhIAheqQ020.jpg",
"link": "https://www.dongqiudi.com/article/5976844",
"time": 1782661185
},
{
"title": "Here we go！罗马诺：莱万即将自由转会加盟芝加哥火焰",
"img": "https://bdimg7.qunliao.info/fastdfs8/M00/5B/CC/rBXRn2pBW7GAV2RBAA6I_piRFKQ343.jpg",
"link": "https://www.dongqiudi.com/article/5977120",
"time": 1782668126
},
{
"title": "豪门对阵，日本近10场比赛7胜3平，蓝武士冲击16强能否如愿？看热门情报>>",
"img": "https://bdimg7.qunliao.info/fastdfs8/M00/5B/FD/rBXRn2pBbsCAMO-7AABzoFJSLfU218.jpg",
"link": "https://www.dongqiudi.com/article/5977251",
"time": 1782673168
},
{
"title": "莫雷托：朗格莱将自由身加盟本菲卡，西蒙尼明确他不在计划内",
"img": "https://bdimg7.qunliao.info/fastdfs8/M00/5C/18/rBXRDGpBcp2AREihAAdJFObOwRg062.jpg",
"link": "https://www.dongqiudi.com/article/5977284",
"time": 1782674081
},
{
"title": "卡纳瓦罗：我不会责怪我的球员，乌兹别克斯坦足球需投资未来",
"img": "https://bdimg7.qunliao.info/fastdfs8/M00/5C/14/rBXRDGpBcV-AYCrWAAGWDZzwb1c652.jpg",
"link": "https://www.dongqiudi.com/article/5977192",
"time": 1782673777
},
{
"title": "德天空：拜仁17岁小将达尼奥科将加盟沃尔夫斯堡",
"img": "https://bdimg7.qunliao.info/fastdfs8/M00/5B/FA/rBXRn2pBbduAPssvAAGEWa84d1s922.jpg",
"link": "https://www.dongqiudi.com/article/5977239",
"time": 1782672956
},
{
"title": "德巴斯特：我参加了部分合练；等了这么久才知道对手是谁很怪",
"img": "https://bdimg7.qunliao.info/fastdfs8/M00/5C/00/rBXRDGpBaW-AVCPaAATUVn1qCPg126.jpg",
"link": "https://www.dongqiudi.com/article/5977215",
"time": 1782672314
},
{
"title": "DO：若今夏离开莱比锡，迪奥曼德选择加盟大巴黎",
"img": "https://bdimg7.qunliao.info/fastdfs8/M00/5B/F4/rBXRn2pBaveANjlOAACifTOAj4I380.jpg",
"link": "https://www.dongqiudi.com/article/5977220",
"time": 1782672313
},
{
"title": "德国队营地玩捉迷藏，哈弗茨笑称像14岁",
"img": "https://bdimg7.qunliao.info/fastdfs8/M00/5B/E3/rBXRDGpBXl6APqZZAAEZgDD-n1M399.jpg",
"link": "https://www.dongqiudi.com/article/5977193",
"time": 1782671975
},
{
"title": "约旦世界杯小组赛末轮对阵阿根廷，约旦国王现场观战",
"img": "https://bdimg7.qunliao.info/fastdfs8/M00/5B/F4/rBXRDGpBZDCACT4yAAG4xEh8d0M917.jpg",
"link": "https://www.dongqiudi.com/article/5977212",
"time": 1782671887
},
{
"title": "马卡：阿贾克斯正与巴萨谈租借特狮，只愿付球员10-15%的薪水",
"img": "https://bdimg7.qunliao.info/fastdfs8/M00/5B/F9/rBXRDGpBZd2ATIBjAAD7unhSgPc034.jpg",
"link": "https://www.dongqiudi.com/article/5977198",
"time": 1782670968
},
{
"title": "天空：纽卡有意瑞士中场曼赞比，球员估值约4200万镑",
"img": "https://bdimg7.qunliao.info/fastdfs8/M00/5B/F5/rBXRDGpBZHKAPJKmAAInZva6WQM183.jpg",
"link": "https://www.dongqiudi.com/article/5977191",
"time": 1782670622
},
{
"title": "格雷戈里奇：2-3落后的时候我真的以为已经没戏了；我们踢得太松",
"img": "https://bdimg7.qunliao.info/fastdfs8/M00/5B/F4/rBXRDGpBY8-AXvQxAAGNuqnGvuI245.jpg",
"link": "https://www.dongqiudi.com/article/5977187",
"time": 1782670353
},
{
"title": "邮报：乌加特受伤不太可能影响曼联引进埃德松和M费的财力",
"img": "https://bdimg7.qunliao.info/fastdfs8/M00/5B/F0/rBXRDGpBYraAYte2ACfotDChnXc622.jpg",
"link": "https://www.dongqiudi.com/article/5977182",
"time": 1782670310
},
{
"title": "约旦球迷调侃乔丹：对不起迈克尔，但“Jordan”是我们先的",
"img": "https://bdimg7.qunliao.info/fastdfs8/M00/5B/E8/rBXRDGpBYCuAJg5zAADjRda7Yok463.jpg",
"link": "https://www.dongqiudi.com/article/5977150",
"time": 1782669515
},
{
"title": "多大仇？韩国KBS电视台在洪明甫辞职的发布会上为其打码",
"img": "https://bdimg7.qunliao.info/fastdfs8/M00/5B/D7/rBXRn2pBX-yAKJ1eAAGLKDp4R6c925.jpg",
"link": "https://www.dongqiudi.com/article/5977144",
"time": 1782669302
},
{
"title": "世体：莱万加盟芝加哥火焰预计周一官宣",
"img": "https://bdimg7.qunliao.info/fastdfs8/M00/5B/D6/rBXRn2pBX1SAHkMaAADgOUEMvcc705.jpg",
"link": "https://www.dongqiudi.com/article/5977146",
"time": 1782669298
}
]
}