{
"items": [
{
"title": "世界杯第十比赛日前瞻：马宁世界杯主裁首秀，荷兰德国出战",
"img": "https://bdimg7.qunliao.info/fastdfs8/M00/3B/C2/rBXRDGo1GCGASHaYAAQ20sT4BNU268.jpg",
"link": "https://www.dongqiudi.com/article/5948588",
"time": 1781949600
},
{
"title": "旧文新发丨裁判抽筋却被投喂腌黄瓜汁，为什么？",
"img": "https://bdimg7.qunliao.info/fastdfs7/M00/86/73/rBUBsmZ1SwaAfBEIAAuA8pKvnPU463.png",
"link": "https://www.dongqiudi.com/article/4343180",
"time": 1718964000
},
{
"title": "国旗只有蓝白红，橙色为何成为荷兰人的最爱？",
"img": "https://bdimg7.qunliao.info/fastdfs8/M00/3E/EC/rBXRn2o2VcOAJhrRAASQlVKcmFU585.jpg",
"link": "https://www.dongqiudi.com/article/5945969",
"time": 1781953200
},
{
"title": "科特迪瓦防守硬朗、反击犀利，德国这场能赢球吗？18钻看看专家意见>>",
"img": "https://bdimg7.qunliao.info/fastdfs8/M00/3F/5E/rBXRDGo2ei-AKVnjAAA22OEzOoM973.png",
"link": "https://www.dongqiudi.com/article/5951905",
"time": 1781946045
},
{
"title": "海地主帅：球队没彻底崩溃，球员已证明自己配得上世界杯舞台",
"img": "https://bdimg7.qunliao.info/fastdfs8/M00/3F/69/rBXRDGo2fsWAWZxUAAEm5DAgp2Y609.jpg",
"link": "https://www.dongqiudi.com/article/5952291",
"time": 1781956296
},
{
"title": "14连红+比分命中！蓝月说球：美国带走3分，提前看准攻防状态",
"img": "https://bdimg7.qunliao.info/fastdfs8/M00/3F/69/rBXRDGo2fqqAUh2EAAAvdws7-gE757.png",
"link": "https://www.dongqiudi.com/article/5952301",
"time": 1781956280
},
{
"title": "半场：青岛海牛2-1无锡吴钩，刘国宝、郑传辉、孙智轩破门",
"img": "https://bdimg7.qunliao.info/fastdfs8/M00/3F/53/rBXRn2o2euqAZJACAAW4uLklKYA730.jpg",
"link": "https://www.dongqiudi.com/article/5952289",
"time": 1781956104
},
{
"title": "意媒：萨格勒布迪纳摩想留住本纳赛尔，但球员需先和米兰商量",
"img": "https://bdimg7.qunliao.info/fastdfs8/M00/F5/E8/rBXRn2oaD46AEoYgAAE3WhmmWGY538.jpg",
"link": "https://www.dongqiudi.com/article/5952216",
"time": 1781955673
},
{
"title": "Here we go！罗马诺：卡塞米罗将加盟迈阿密国际",
"img": "https://bdimg7.qunliao.info/fastdfs8/M00/3F/58/rBXRn2o2fFCAYDGGAA5UyBSsS-s240.png",
"link": "https://www.dongqiudi.com/article/5952266",
"time": 1781955471
},
{
"title": "罗体：德劳伦蒂斯将现场观战德布劳内和卢卡库，查看二人状态",
"img": "https://bdimg7.qunliao.info/fastdfs8/M00/35/8B/rBXRn2oywz-AImWuAAHr6a9KfVY414.jpg",
"link": "https://www.dongqiudi.com/article/5952210",
"time": 1781955422
},
{
"title": "12连红+命中比分！专家足球老炮儿：澳大利亚难挡美国攻势",
"img": "https://bdimg7.qunliao.info/fastdfs8/M00/3F/60/rBXRDGo2eyiAKMgLAAAvdws7-gE304.png",
"link": "https://www.dongqiudi.com/article/5952263",
"time": 1781955373
},
{
"title": "每体：赛巴里拒谈拜仁转会，称瓜帅观战是荣幸",
"img": "https://bdimg7.qunliao.info/fastdfs8/M00/3F/5D/rBXRDGo2egyAAGwrAAII2-LjAt8494.jpg",
"link": "https://www.dongqiudi.com/article/5952245",
"time": 1781955331
}
]
}