{
"items": [
{
"title": "C罗状态回来了，但哥伦比亚手打平就能第一，最终谁会拿下k组第一呢？看看专家怎么说>>",
"img": "https://bdimg7.qunliao.info/fastdfs8/M00/56/1E/rBXRn2o_Pc-AfOcjAACBHLFK3UE205.jpg",
"link": "https://www.dongqiudi.com/article/5970691",
"time": 1782529494
},
{
"title": "签即战力，TA：切尔西认为更衣室内需要更多成熟的声音",
"img": "https://bdimg7.qunliao.info/fastdfs8/M00/58/BC/rBXRn2pAOiKAbNNdAAGXx_mCXkg026.jpg",
"link": "https://www.dongqiudi.com/article/5973785",
"time": 1782594108
},
{
"title": "德天空：贝西克塔斯500万+500万欧报价努贝尔，已被拜仁拒绝",
"img": "https://bdimg7.qunliao.info/fastdfs8/M00/58/BB/rBXRn2pAOeeAIDfJABCtNh101TI092.png",
"link": "https://www.dongqiudi.com/article/5973823",
"time": 1782594026
},
{
"title": "经纪人：意大利足球是结构性问题，国米抢人也拼不过英超",
"img": "https://bdimg7.qunliao.info/fastdfs8/M00/58/BC/rBXRDGpANPKAGMsfAAB-SWwkqxg799.jpg",
"link": "https://www.dongqiudi.com/article/5973807",
"time": 1782593596
},
{
"title": "咒术回战？秘鲁电视台请人给凯恩驱魔",
"img": "https://bdimg7.qunliao.info/fastdfs8/M00/58/C3/rBXRDGpAOB6AE2yLAAE80umpXbQ440.jpg",
"link": "https://www.dongqiudi.com/article/5973816",
"time": 1782593571
},
{
"title": "记者：河床功勋主帅加利亚多进入乌拉圭新帅候选名单",
"img": "https://bdimg7.qunliao.info/fastdfs8/M00/58/AF/rBXRn2pANkKAf9-iAAC15pJSHNA364.jpg",
"link": "https://www.dongqiudi.com/article/5973803",
"time": 1782593399
},
{
"title": "跟队记者：劳塔罗和小蜘蛛将联袂首发，梅西下半场替补",
"img": "https://bdimg7.qunliao.info/fastdfs8/M00/58/BE/rBXRDGpANj-AF_4GAAFB4B31UrM107.jpg",
"link": "https://www.dongqiudi.com/article/5973804",
"time": 1782593094
},
{
"title": "罗马诺：扎卡已告知桑德兰他想去切尔西，谈判正在进行中",
"img": "https://bdimg7.qunliao.info/fastdfs8/M00/58/B6/rBXRDGpAMmiABkb3AAIQNKheY9Q691.jpg",
"link": "https://www.dongqiudi.com/article/5973791",
"time": 1782592582
},
{
"title": "队报：民主刚果网红球迷没能拿到美国签证，无缘球队生死战",
"img": "https://bdimg7.qunliao.info/fastdfs8/M00/58/AC/rBXRDGpALrCAOcmLAAKSB_3fPpw376.jpg",
"link": "https://www.dongqiudi.com/article/5973786",
"time": 1782592529
},
{
"title": "阿斯：科莫同意6000万欧签下尼科-帕斯，预计下周官宣",
"img": "https://bdimg7.qunliao.info/fastdfs8/M00/58/A4/rBXRn2pAMcyAM16wAAC9baqsmlY457.jpg",
"link": "https://www.dongqiudi.com/article/5973779",
"time": 1782592281
},
{
"title": "斯基拉：米兰已经询问了安东尼奥-席尔瓦的情况",
"img": "https://bdimg7.qunliao.info/fastdfs8/M00/58/B3/rBXRDGpAMiOAPKF1AAFuE7gew_E055.jpg",
"link": "https://www.dongqiudi.com/article/5973782",
"time": 1782592254
},
{
"title": "意媒：沙特俱乐部愿意3000万买苏莱，球员可能接受1200万年薪",
"img": "https://bdimg7.qunliao.info/fastdfs8/M00/58/A8/rBXRDGpALWiAHJghAAARXu1J3Uw599.jpg",
"link": "https://www.dongqiudi.com/article/5973784",
"time": 1782592214
},
{
"title": "留洋球员，英格兰队世界杯首发首次有4人来自非英格兰俱乐部",
"img": "https://bdimg7.qunliao.info/fastdfs8/M00/58/AE/rBXRDGpAL-CAMx3RAANEB4r4ifw928.jpg",
"link": "https://www.dongqiudi.com/article/5973773",
"time": 1782591774
},
{
"title": "赛前传统，阿根廷足协主席晒与梅西、德保罗合照",
"img": "https://bdimg7.qunliao.info/fastdfs8/M00/58/AE/rBXRDGpAL4eAOmKlABHwE4E7IcI116.png",
"link": "https://www.dongqiudi.com/article/5973769",
"time": 1782591378
},
{
"title": "莱罗塔列：米兰应先定风格再谈贡萨洛-拉莫斯转会",
"img": "https://bdimg7.qunliao.info/fastdfs8/M00/58/8E/rBXRn2pAKYiAC18wAAGG0j4gxlA757.jpg",
"link": "https://www.dongqiudi.com/article/5973764",
"time": 1782591113
},
{
"title": "罗马诺：米兰现在的优先目标是中后卫；和卡萨多没有具体讨论",
"img": "https://bdimg7.qunliao.info/fastdfs8/M00/58/A7/rBXRDGpALLKAJbVjAAHnGnbpe80120.jpg",
"link": "https://www.dongqiudi.com/article/5973760",
"time": 1782590975
},
{
"title": "图赫尔：不是说拉什福德换戈登问题就都解决了，这只是轮换",
"img": "https://bdimg7.qunliao.info/fastdfs8/M00/58/99/rBXRn2pALIqAcpVMAAOsMDp7_pw815.jpg",
"link": "https://www.dongqiudi.com/article/5973754",
"time": 1782590921
},
{
"title": "尼科-威廉斯：故事还没有结束，我们会尽快在本届世界杯再见",
"img": "https://bdimg7.qunliao.info/fastdfs8/M00/58/A0/rBXRDGpAKreAWwFsAAPKTz8rw6s020.jpg",
"link": "https://www.dongqiudi.com/article/5973734",
"time": 1782590679
}
]
}